wmul_test_utils/__init__.py
wmul_test_utils-0.7.1.dist-info/LICENSE
wmul_test_utils-0.7.1.dist-info/WHEEL
wmul_test_utils-0.7.1.dist-info/METADATA
wmul_test_utils-0.7.1.dist-info/RECORD
