Metadata-Version: 2.1
Name: wmul-test-utils
Version: 0.7.1
Summary: Various utilities for testing WMUL-FM's other packages.
Author-email: Michael Stanley <stanley50@marshall.edu>
Requires-Python: >=3.9
Classifier: Programming Language :: Python :: 3
Classifier: License :: OSI Approved :: GNU General Public License v2 (GPLv2)
Classifier: Operating System :: OS Independent
Classifier: Development Status :: 5 - Production/Stable
Classifier: Topic :: Software Development :: Testing
Requires-Dist: faker
Requires-Dist: pytest ; extra == "test"
Requires-Dist: pytest-mock ; extra == "test"
Requires-Dist: tox ; extra == "tox"
Project-URL: Bug Tracker, https://github.com/MikeTheHammer/wmul_test_utils/issues
Project-URL: Homepage, https://github.com/MikeTheHammer/wmul_test_utils
Provides-Extra: test
Provides-Extra: tox
